matchreport/__init__.py
matchreport/constants.py
matchreport/matchreporter.py
matchreport-0.1.dist-info/LICENSE
matchreport-0.1.dist-info/METADATA
matchreport-0.1.dist-info/WHEEL
matchreport-0.1.dist-info/entry_points.txt
matchreport-0.1.dist-info/top_level.txt
matchreport-0.1.dist-info/RECORD
