Metadata-Version: 2.1
Name: matchreport
Version: 0.1
Summary: Creates analysis reports for GAA matches
Home-page: https://github.com/moynihanrory/matchreport
Author: Rory Moynihan
Author-email: ruaraidho@gmail.com
License: MIT
Platform: UNKNOWN
Classifier: Development Status :: 3 - Alpha
Classifier: License :: OSI Approved :: MIT License
Classifier: Programming Language :: Python :: 3.5
Classifier: Natural Language :: English
Classifier: Topic :: Text Processing :: Linguistic
Requires-Dist: pandas
Requires-Dist: xmltodict
